secret_store_client/__init__.py
secret_store_client/client.py
nevermined_secret_store-0.1.1.dist-info/LICENSE
nevermined_secret_store-0.1.1.dist-info/METADATA
nevermined_secret_store-0.1.1.dist-info/NOTICE
nevermined_secret_store-0.1.1.dist-info/WHEEL
nevermined_secret_store-0.1.1.dist-info/top_level.txt
nevermined_secret_store-0.1.1.dist-info/RECORD
